ipcbroker/__init__.py
ipcbroker/broker.py
ipcbroker/client.py
ipcbroker/message.py
ipcbroker/threaded.py
ipcbroker-0.4.dist-info/DESCRIPTION.rst
ipcbroker-0.4.dist-info/METADATA
ipcbroker-0.4.dist-info/RECORD
ipcbroker-0.4.dist-info/WHEEL
ipcbroker-0.4.dist-info/metadata.json
ipcbroker-0.4.dist-info/top_level.txt
