Metadata-Version: 2.0
Name: ipcbroker
Version: 0.4
Summary: Interprocess communication framework
Home-page: https://github.com/DaGuich/ipcbroker
Author: Matthias Gilch
Author-email: matthias.gilch.mg@gmail.com
License: UNKNOWN
Download-URL: https://github.com/DaGuich/ipcbroker/archive/0.4.tar.gz
Keywords: IPC,interprocess,communication,broker,client
Platform: UNKNOWN
